{
  "name": "mitigation_cb-400mt~0007",
  "data": [
    {
      "seriesName": "SEAI_BIOENERGY",
      "seriesValues": [
        [
          2018,
          31.172379652083826
        ],
        [
          2019,
          31.861253464511677
        ],
        [
          2020,
          32.572347175307144
        ],
        [
          2021,
          37.158968989424366
        ],
        [
          2022,
          40.87640366856142
        ],
        [
          2023,
          42.91839307375659
        ],
        [
          2024,
          52.37091902487299
        ],
        [
          2025,
          51.61594247634742
        ],
        [
          2026,
          57.25424698509394
        ],
        [
          2027,
          63.99942975571483
        ],
        [
          2028,
          66.72169528915367
        ],
        [
          2029,
          72.61009962602714
        ],
        [
          2030,
          76.79754034723805
        ],
        [
          2031,
          73.75056623757472
        ],
        [
          2032,
          82.29090428493123
        ],
        [
          2033,
          82.79196956100935
        ],
        [
          2034,
          83.0699422194923
        ],
        [
          2035,
          83.14536647679729
        ],
        [
          2036,
          83.60805908878258
        ],
        [
          2037,
          84.00512666803422
        ],
        [
          2038,
          84.52806146820164
        ],
        [
          2039,
          90.34641913502753
        ],
        [
          2040,
          113.74161357948276
        ],
        [
          2041,
          121.64967038715342
        ],
        [
          2042,
          123.8744982226364
        ],
        [
          2043,
          126.09977134149855
        ],
        [
          2044,
          128.3254954244981
        ],
        [
          2045,
          130.55168166510606
        ],
        [
          2046,
          132.77846036681774
        ],
        [
          2047,
          135.1355641458267
        ],
        [
          2048,
          137.234021863846
        ],
        [
          2049,
          139.1068378942383
        ],
        [
          2050,
          141.33337209665802
        ],
        [
          2051,
          141.36120765836097
        ]
      ]
    },
    {
      "seriesName": "SEAI_COAL",
      "seriesValues": [
        [
          2018,
          34.03604184358554
        ],
        [
          2019,
          17.33462372296546
        ],
        [
          2020,
          19.605577859335554
        ],
        [
          2021,
          39.760688688916545
        ],
        [
          2022,
          32.52614458558462
        ],
        [
          2023,
          10.13058189612868
        ],
        [
          2024,
          8.42248582980149
        ],
        [
          2025,
          5.8556042116984
        ],
        [
          2026,
          4.742816636602089
        ],
        [
          2027,
          4.667084285252383
        ],
        [
          2028,
          4.5282459990671935
        ],
        [
          2029,
          4.438305462338079
        ],
        [
          2030,
          4.600927015220555
        ],
        [
          2031,
          5.1177877436187185
        ],
        [
          2032,
          5.72490180074822
        ],
        [
          2033,
          6.3891454318950105
        ],
        [
          2034,
          7.11619942930864
        ],
        [
          2035,
          7.912312424090439
        ],
        [
          2036,
          8.41679714358824
        ],
        [
          2037,
          6.035929694338
        ],
        [
          2038,
          5.07610050101443
        ],
        [
          2039,
          4.9921894747692095
        ],
        [
          2040,
          4.226552577917153
        ],
        [
          2041,
          3.8767616715568747
        ],
        [
          2042,
          3.421718651881066
        ],
        [
          2043,
          3.0096765554764033
        ],
        [
          2044,
          2.5932214020349384
        ],
        [
          2045,
          2.172330427048608
        ],
        [
          2046,
          1.7469639393455387
        ],
        [
          2047,
          1.3304991806050466
        ],
        [
          2048,
          0.8826911944576645
        ],
        [
          2049,
          0.4436789716638913
        ],
        [
          2050,
          4.815549938546506e-05
        ],
        [
          2051,
          7.519426110538606e-05
        ]
      ]
    },
    {
      "seriesName": "SEAI_ELECTRICITY",
      "seriesValues": [
        [
          2018,
          -0.09984571699363531
        ],
        [
          2019,
          2.320763102154408
        ],
        [
          2020,
          -0.5467721172630355
        ],
        [
          2021,
          5.716363956274213
        ],
        [
          2022,
          0.9069960298942288
        ],
        [
          2023,
          5.99999985092446
        ],
        [
          2024,
          5.999999850828129
        ],
        [
          2025,
          5.999999036828652
        ],
        [
          2026,
          5.999999043743891
        ],
        [
          2027,
          5.99999904328612
        ],
        [
          2028,
          5.999999042631475
        ],
        [
          2029,
          5.999999041857461
        ],
        [
          2030,
          5.999998832088407
        ],
        [
          2031,
          5.9999986354007095
        ],
        [
          2032,
          5.999998444779555
        ],
        [
          2033,
          5.999998564902926
        ],
        [
          2034,
          5.999998564004633
        ],
        [
          2035,
          5.999999515148685
        ],
        [
          2036,
          5.999999552956917
        ],
        [
          2037,
          5.999999489252859
        ],
        [
          2038,
          5.999993458215121
        ],
        [
          2039,
          5.999998732541066
        ],
        [
          2040,
          2.7463772327924723
        ],
        [
          2041,
          -0.5342655476020184
        ],
        [
          2042,
          -0.1426325132816082
        ],
        [
          2043,
          -1.771487917708214
        ],
        [
          2044,
          -5.019231105704327
        ],
        [
          2045,
          -6.597745535235267
        ],
        [
          2046,
          -9.305122839019258
        ],
        [
          2047,
          -12.762304338858735
        ],
        [
          2048,
          -18.182780656012074
        ],
        [
          2049,
          -22.466430505535072
        ],
        [
          2050,
          -24.07365713771437
        ],
        [
          2051,
          -24.609415172648514
        ]
      ]
    },
    {
      "seriesName": "SEAI_NATGAS",
      "seriesValues": [
        [
          2018,
          185.2297430149875
        ],
        [
          2019,
          191.93975817063932
        ],
        [
          2020,
          192.94851895387933
        ],
        [
          2021,
          186.13297766752797
        ],
        [
          2022,
          197.41884812142953
        ],
        [
          2023,
          189.88351835864088
        ],
        [
          2024,
          192.3568997371629
        ],
        [
          2025,
          197.73820240189173
        ],
        [
          2026,
          191.6891327264228
        ],
        [
          2027,
          191.7195500559728
        ],
        [
          2028,
          174.78000876227617
        ],
        [
          2029,
          152.0222495599998
        ],
        [
          2030,
          122.1110957712948
        ],
        [
          2031,
          113.5927757075064
        ],
        [
          2032,
          112.6715658923023
        ],
        [
          2033,
          112.84109029858459
        ],
        [
          2034,
          113.09115389752264
        ],
        [
          2035,
          90.58425634728141
        ],
        [
          2036,
          87.76404480886038
        ],
        [
          2037,
          82.15574331347209
        ],
        [
          2038,
          79.28020325851398
        ],
        [
          2039,
          67.70836485370674
        ],
        [
          2040,
          59.49001858775634
        ],
        [
          2041,
          55.14360069283279
        ],
        [
          2042,
          52.94061037419718
        ],
        [
          2043,
          52.18009897244687
        ],
        [
          2044,
          50.31891694890794
        ],
        [
          2045,
          47.60965650195836
        ],
        [
          2046,
          45.89082124226327
        ],
        [
          2047,
          45.30053282884096
        ],
        [
          2048,
          44.50134191027257
        ],
        [
          2049,
          43.81383700390398
        ],
        [
          2050,
          43.40360814532305
        ],
        [
          2051,
          43.50145220041871
        ]
      ]
    },
    {
      "seriesName": "SEAI_OIL",
      "seriesValues": [
        [
          2018,
          308.36713472870485
        ],
        [
          2019,
          296.00632643262657
        ],
        [
          2020,
          242.8153665340718
        ],
        [
          2021,
          256.8460328074526
        ],
        [
          2022,
          289.12929187156993
        ],
        [
          2023,
          286.39251704608495
        ],
        [
          2024,
          291.48772850582293
        ],
        [
          2025,
          286.12464304299044
        ],
        [
          2026,
          270.52711535265075
        ],
        [
          2027,
          251.54845184074978
        ],
        [
          2028,
          236.95628812296454
        ],
        [
          2029,
          223.68889686102406
        ],
        [
          2030,
          211.99803830991374
        ],
        [
          2031,
          198.53266446852203
        ],
        [
          2032,
          173.89955428051766
        ],
        [
          2033,
          154.81354853814597
        ],
        [
          2034,
          134.66912080297647
        ],
        [
          2035,
          116.94482559395455
        ],
        [
          2036,
          104.92946522325165
        ],
        [
          2037,
          97.27009538133755
        ],
        [
          2038,
          91.32708128470517
        ],
        [
          2039,
          86.02146223121561
        ],
        [
          2040,
          84.00865091146778
        ],
        [
          2041,
          81.56430929310586
        ],
        [
          2042,
          83.09080117656498
        ],
        [
          2043,
          82.83193770785718
        ],
        [
          2044,
          82.34881065252218
        ],
        [
          2045,
          80.68269842048619
        ],
        [
          2046,
          80.14171317923223
        ],
        [
          2047,
          80.13038344863729
        ],
        [
          2048,
          80.18684130469236
        ],
        [
          2049,
          80.15238232406568
        ],
        [
          2050,
          80.06251086655462
        ],
        [
          2051,
          80.66014337183708
        ]
      ]
    },
    {
      "seriesName": "SEAI_OTHER_RENEWABLES",
      "seriesValues": [
        [
          2018,
          36.085304223155035
        ],
        [
          2019,
          41.77574885378917
        ],
        [
          2020,
          44.73125436234388
        ],
        [
          2021,
          42.14982094386087
        ],
        [
          2022,
          48.63253008461126
        ],
        [
          2023,
          63.16761492885728
        ],
        [
          2024,
          72.40065216357931
        ],
        [
          2025,
          80.34723707409412
        ],
        [
          2026,
          94.07317758400494
        ],
        [
          2027,
          103.35357653042499
        ],
        [
          2028,
          124.7085491107114
        ],
        [
          2029,
          148.05328292870567
        ],
        [
          2030,
          175.45442331348232
        ],
        [
          2031,
          197.48610288471866
        ],
        [
          2032,
          207.89505347057093
        ],
        [
          2033,
          218.13409646319693
        ],
        [
          2034,
          228.6972164677004
        ],
        [
          2035,
          255.08070903343446
        ],
        [
          2036,
          264.14654095252445
        ],
        [
          2037,
          275.10832953733996
        ],
        [
          2038,
          283.43346009265724
        ],
        [
          2039,
          293.739000236395
        ],
        [
          2040,
          299.8737723149344
        ],
        [
          2041,
          308.59998677082285
        ],
        [
          2042,
          311.22742261477686
        ],
        [
          2043,
          318.9503487883852
        ],
        [
          2044,
          327.7058330183275
        ],
        [
          2045,
          336.7310638776834
        ],
        [
          2046,
          343.2049860852815
        ],
        [
          2047,
          350.6561587444174
        ],
        [
          2048,
          360.4975726087555
        ],
        [
          2049,
          368.8426315299923
        ],
        [
          2050,
          373.9584425717874
        ],
        [
          2051,
          378.11987159666194
        ]
      ]
    },
    {
      "seriesName": "SEAI_PEAT",
      "seriesValues": [
        [
          2018,
          28.1626709488555
        ],
        [
          2019,
          25.9000000025602
        ],
        [
          2020,
          17.0000000030408
        ],
        [
          2021,
          10.6000000019321
        ],
        [
          2022,
          8.90000000573063
        ],
        [
          2023,
          1.40342378552071
        ],
        [
          2024,
          0.539548720226058
        ],
        [
          2025,
          0.501008569584456
        ],
        [
          2026,
          0.256358238101319
        ],
        [
          2027,
          0.0284999704421568
        ],
        [
          2028,
          3.35978930528912e-06
        ],
        [
          2029,
          3.05919777413961e-06
        ],
        [
          2030,
          5.36206658288407e-06
        ],
        [
          2031,
          0.500005393470451
        ],
        [
          2032,
          1.05000558998265
        ],
        [
          2033,
          1.65500547958313
        ],
        [
          2034,
          2.3205043206811
        ],
        [
          2035,
          3.0525509323904
        ],
        [
          2036,
          0.778912317920771
        ],
        [
          2037,
          0.389458771150901
        ],
        [
          2038,
          8.75314970494978e-06
        ],
        [
          2039,
          8.31353034076216e-06
        ],
        [
          2040,
          7.86527428491971e-06
        ],
        [
          2041,
          8.37922416546894e-06
        ],
        [
          2042,
          5.40337437275974e-06
        ],
        [
          2043,
          5.55458869555035e-06
        ],
        [
          2044,
          5.40466451918714e-06
        ],
        [
          2045,
          5.04156168259865e-06
        ],
        [
          2046,
          4.99323389121472e-06
        ],
        [
          2047,
          7.44429214987977e-06
        ],
        [
          2048,
          4.97572832377002e-06
        ],
        [
          2049,
          4.75861630136687e-06
        ],
        [
          2050,
          4.77562416425769e-06
        ],
        [
          2051,
          6.1017175813045e-06
        ]
      ]
    },
    {
      "seriesName": "SEAI_HYDROGEN",
      "seriesValues": [
        [
          2025,
          0.310910220732692
        ],
        [
          2026,
          0.393471194702717
        ],
        [
          2027,
          0.463802472194222
        ],
        [
          2028,
          0.534154838420719
        ],
        [
          2029,
          0.604528342327106
        ]
      ]
    }
  ]
}