{
  "name": "mitigation_cb-315mt~0010",
  "data": [
    {
      "seriesName": "INDDST",
      "seriesValues": [
        [
          2018,
          0.0304166014386515
        ],
        [
          2019,
          0.0193793713784629
        ],
        [
          2020,
          0.0204008021799799
        ],
        [
          2021,
          0.0206567594468181
        ],
        [
          2022,
          0.0274707326295722
        ],
        [
          2023,
          0.0286965255538147
        ],
        [
          2024,
          0.0298381861872507
        ],
        [
          2025,
          0.0310087728401182
        ],
        [
          2026,
          0.0322003815746718
        ],
        [
          2027,
          0.033430241786925
        ],
        [
          2028,
          0.0346907846683765
        ],
        [
          2029,
          0.0359827653006093
        ],
        [
          2030,
          0.0373068969539591
        ],
        [
          2031,
          0.0382775748729708
        ],
        [
          2032,
          0.030831873646611
        ],
        [
          2033,
          0.0247571991987006
        ],
        [
          2034,
          0.0241185863956779
        ],
        [
          2035,
          0.0233892360390064
        ],
        [
          2036,
          0.0225822537067908
        ],
        [
          2037,
          0.0216836169625548
        ],
        [
          2038,
          0.0206929861528269
        ],
        [
          2039,
          0.0196048675991018
        ],
        [
          2040,
          0.0184155903925541
        ],
        [
          2041,
          0.0171223714697409
        ],
        [
          2042,
          0.0157187248073028
        ],
        [
          2043,
          0.0142013498063504
        ],
        [
          2044,
          0.0125658372804347
        ],
        [
          2045,
          0.0108077784059928
        ],
        [
          2046,
          0.008922675878002299
        ],
        [
          2047,
          0.0069049714180453
        ],
        [
          2048,
          0.004750086609978871
        ],
        [
          2049,
          0.0024531863874564896
        ],
        [
          2050,
          1.4917038808752423e-05
        ],
        [
          2051,
          0.00041532503498103334
        ]
      ]
    },
    {
      "seriesName": "INDELC",
      "seriesValues": [
        [
          2018,
          3.693431126731324
        ],
        [
          2019,
          4.066813580501545
        ],
        [
          2020,
          3.7875586475725145
        ],
        [
          2021,
          3.7882699864978044
        ],
        [
          2022,
          5.037893416274296
        ],
        [
          2023,
          5.241173865598089
        ],
        [
          2024,
          5.44966318951071
        ],
        [
          2025,
          5.663301409799009
        ],
        [
          2026,
          5.882218833595278
        ],
        [
          2027,
          6.106542016933919
        ],
        [
          2028,
          6.336409501999505
        ],
        [
          2029,
          6.5719590556267935
        ],
        [
          2030,
          6.813331771213689
        ],
        [
          2031,
          7.060570226990148
        ],
        [
          2032,
          7.31392956631578
        ],
        [
          2033,
          7.573567155861078
        ],
        [
          2034,
          7.839640797561642
        ],
        [
          2035,
          8.112314821664329
        ],
        [
          2036,
          8.39175252457527
        ],
        [
          2037,
          8.678127647371216
        ],
        [
          2038,
          8.971608881703721
        ],
        [
          2039,
          9.272379541594232
        ],
        [
          2040,
          9.580631227533466
        ],
        [
          2041,
          9.89654323136634
        ],
        [
          2042,
          10.220314413660947
        ],
        [
          2043,
          10.552133795570995
        ],
        [
          2044,
          10.892228539294747
        ],
        [
          2045,
          11.240803024041107
        ],
        [
          2046,
          11.59805105046786
        ],
        [
          2047,
          11.964225868115603
        ],
        [
          2048,
          12.339545821508771
        ],
        [
          2049,
          12.7242522501614
        ],
        [
          2050,
          13.11857438530935
        ],
        [
          2051,
          13.522772379694473
        ]
      ]
    },
    {
      "seriesName": "INDGAS",
      "seriesValues": [
        [
          2018,
          0.8589201647094169
        ],
        [
          2019,
          0.8431779022821425
        ],
        [
          2020,
          0.8729545871659781
        ],
        [
          2021,
          0.8388913099433233
        ],
        [
          2022,
          1.1156134657198624
        ],
        [
          2023,
          1.1124504245908957
        ],
        [
          2024,
          1.1284222758311542
        ],
        [
          2025,
          1.1440836147878375
        ],
        [
          2026,
          1.1587231204348856
        ],
        [
          2027,
          1.172074962053674
        ],
        [
          2028,
          1.0699934236463835
        ],
        [
          2029,
          1.0642865779290036
        ],
        [
          2030,
          1.0958421743168012
        ],
        [
          2031,
          1.194272278076415
        ],
        [
          2032,
          1.2196837603667152
        ],
        [
          2033,
          1.2363014074409968
        ],
        [
          2034,
          1.249442351588533
        ],
        [
          2035,
          1.2616407160471468
        ],
        [
          2036,
          1.2710862582520326
        ],
        [
          2037,
          1.2806905294380868
        ],
        [
          2038,
          1.2904484235435598
        ],
        [
          2039,
          1.300300061583941
        ],
        [
          2040,
          1.3114259399997086
        ],
        [
          2041,
          1.322482729182056
        ],
        [
          2042,
          1.3365372362625083
        ],
        [
          2043,
          1.3524261559806123
        ],
        [
          2044,
          1.3669472804369251
        ],
        [
          2045,
          1.3823941779238431
        ],
        [
          2046,
          1.3989848570082597
        ],
        [
          2047,
          1.4166870333340527
        ],
        [
          2048,
          1.4355211001746113
        ],
        [
          2049,
          1.455684300734631
        ],
        [
          2050,
          1.4742726693953705
        ],
        [
          2051,
          1.5352205767062186
        ]
      ]
    },
    {
      "seriesName": "INDKER",
      "seriesValues": [
        [
          2018,
          0.007720422093356631
        ],
        [
          2019,
          0.010215482790816787
        ],
        [
          2020,
          0.01241167701946918
        ],
        [
          2021,
          0.010824709388858817
        ],
        [
          2022,
          0.014395418448014296
        ],
        [
          2023,
          0.013766423896967602
        ],
        [
          2024,
          0.013827729725883567
        ],
        [
          2025,
          0.013858361976481087
        ],
        [
          2026,
          0.013868795816188877
        ],
        [
          2027,
          0.013852330868296342
        ],
        [
          2028,
          0.013807875612702114
        ],
        [
          2029,
          0.01373422189754343
        ],
        [
          2030,
          0.013630172927707952
        ],
        [
          2031,
          0.013425868359115294
        ],
        [
          2032,
          0.013174914705025811
        ],
        [
          2033,
          0.012884848018480012
        ],
        [
          2034,
          0.012553260668494118
        ],
        [
          2035,
          0.012178214652857757
        ],
        [
          2036,
          0.011758070397392848
        ],
        [
          2037,
          0.011290944704070683
        ],
        [
          2038,
          0.010775246480013339
        ],
        [
          2039,
          0.010208723309793938
        ],
        [
          2040,
          0.009589587791023778
        ],
        [
          2041,
          0.008915599841245157
        ],
        [
          2042,
          0.008184720806774935
        ],
        [
          2043,
          0.007394724055628102
        ],
        [
          2044,
          0.006543330418006363
        ],
        [
          2045,
          0.005628160580564032
        ],
        [
          2046,
          0.004646752341052205
        ],
        [
          2047,
          0.0035965847921069745
        ],
        [
          2048,
          0.0024750421024704147
        ],
        [
          2049,
          0.0012794827104213981
        ],
        [
          2050,
          1.2898716031928412e-05
        ],
        [
          2051,
          0.0385963297549613
        ]
      ]
    },
    {
      "seriesName": "INDLPG",
      "seriesValues": [
        [
          2018,
          0.0603681168041661
        ],
        [
          2019,
          0.0680030643763037
        ],
        [
          2020,
          0.0621059376905068
        ],
        [
          2021,
          0.0683043866507735
        ],
        [
          2022,
          0.0908357167402026
        ],
        [
          2023,
          0.0945106644180774
        ],
        [
          2024,
          0.0982700581958665
        ],
        [
          2025,
          0.1021218470672097
        ],
        [
          2026,
          0.10606743182854769
        ],
        [
          2027,
          0.1101120744375278
        ],
        [
          2028,
          0.1142565444994218
        ],
        [
          2029,
          0.1185023380246617
        ],
        [
          2030,
          0.1228545842857148
        ],
        [
          2031,
          0.1273077921387963
        ],
        [
          2032,
          0.1318763151202669
        ],
        [
          2033,
          0.13655803490358182
        ],
        [
          2034,
          0.1413573654447837
        ],
        [
          2035,
          0.1462740650592796
        ],
        [
          2036,
          0.1513127482018515
        ],
        [
          2037,
          0.1564749734702112
        ],
        [
          2038,
          0.1617679086434887
        ],
        [
          2039,
          0.1671902716488432
        ],
        [
          2040,
          0.1727484844650843
        ],
        [
          2041,
          0.1784446689031955
        ],
        [
          2042,
          0.1842825846161001
        ],
        [
          2043,
          0.1902656245714219
        ],
        [
          2044,
          0.1963978653730592
        ],
        [
          2045,
          0.2026829953015424
        ],
        [
          2046,
          0.2091245349598016
        ],
        [
          2047,
          0.21572703285080919
        ],
        [
          2048,
          0.2224944296430987
        ],
        [
          2049,
          0.2294310745522653
        ],
        [
          2050,
          0.2365411051988021
        ],
        [
          2051,
          0.2438234855694701
        ]
      ]
    },
    {
      "seriesName": "INDBDL",
      "seriesValues": [
        [
          2023,
          8.264021516141075e-05
        ],
        [
          2024,
          8.569036560604539e-05
        ],
        [
          2025,
          8.807659433484997e-05
        ],
        [
          2026,
          9.840496341782233e-05
        ],
        [
          2027,
          0.00010018399791573793
        ],
        [
          2028,
          0.0001017128000630921
        ],
        [
          2029,
          0.00010300815908585412
        ],
        [
          2030,
          0.00010412632590661978
        ],
        [
          2031,
          0.0004906347155228847
        ],
        [
          2032,
          0.009327417178496038
        ],
        [
          2033,
          0.0168276365515595
        ],
        [
          2034,
          0.0189272371083822
        ],
        [
          2035,
          0.021153673847884
        ],
        [
          2036,
          0.0234949032745819
        ],
        [
          2037,
          0.0259657794282579
        ],
        [
          2038,
          0.0285678317192993
        ],
        [
          2039,
          0.0313072643313669
        ],
        [
          2040,
          0.0341889913576571
        ],
        [
          2041,
          0.0372167084820697
        ],
        [
          2042,
          0.0403971001604714
        ],
        [
          2043,
          0.0437363148521693
        ],
        [
          2044,
          0.0472391019087596
        ],
        [
          2045,
          0.0509109917804586
        ],
        [
          2046,
          0.0547575479073139
        ],
        [
          2047,
          0.0587857184740432
        ],
        [
          2048,
          0.0630012807741167
        ],
        [
          2049,
          0.0674103961964588
        ],
        [
          2050,
          0.07201375201058301
        ],
        [
          2051,
          0.0738321729911514
        ]
      ]
    },
    {
      "seriesName": "INDBGS",
      "seriesValues": [
        [
          2023,
          0.048231155123145
        ],
        [
          2024,
          0.0784290355859588
        ],
        [
          2025,
          0.1100780306623139
        ],
        [
          2026,
          0.14391778052862692
        ],
        [
          2027,
          0.1802427808826749
        ],
        [
          2028,
          0.3332289253085437
        ],
        [
          2029,
          0.3910981339338611
        ],
        [
          2030,
          0.4129952652370217
        ],
        [
          2031,
          0.3693153093364544
        ],
        [
          2032,
          0.4000106642391546
        ],
        [
          2033,
          0.440890509278813
        ],
        [
          2034,
          0.486672746256562
        ],
        [
          2035,
          0.5348587995281916
        ],
        [
          2036,
          0.5872955216327882
        ],
        [
          2037,
          0.6411094233631455
        ],
        [
          2038,
          0.6963440412080681
        ],
        [
          2039,
          0.7530986546577771
        ],
        [
          2040,
          0.8102359710212945
        ],
        [
          2041,
          0.8691387358477308
        ],
        [
          2042,
          0.9267842250051962
        ],
        [
          2043,
          0.9843772755115279
        ],
        [
          2044,
          1.045170719188918
        ],
        [
          2045,
          1.1069164912635072
        ],
        [
          2046,
          1.1694393461222405
        ],
        [
          2047,
          1.2328274847539433
        ],
        [
          2048,
          1.2971090295299308
        ],
        [
          2049,
          1.3621401019070767
        ],
        [
          2050,
          1.4308753046798417
        ],
        [
          2051,
          1.4594362435899875
        ]
      ]
    },
    {
      "seriesName": "INDBKE",
      "seriesValues": [
        [
          2023,
          0.0012131335307450895
        ],
        [
          2024,
          0.0017475990906408825
        ],
        [
          2025,
          0.0023274461477258627
        ],
        [
          2026,
          0.0029425608831850102
        ],
        [
          2027,
          0.003600038345161089
        ],
        [
          2028,
          0.004301341972552088
        ],
        [
          2029,
          0.00504806406715258
        ],
        [
          2030,
          0.005841845539738024
        ],
        [
          2031,
          0.006752343039776453
        ],
        [
          2032,
          0.007726397938632168
        ],
        [
          2033,
          0.008758406870195213
        ],
        [
          2034,
          0.00985045026396242
        ],
        [
          2035,
          0.011004676526855547
        ],
        [
          2036,
          0.012223330040967142
        ],
        [
          2037,
          0.013508680486032345
        ],
        [
          2038,
          0.014863095492691917
        ],
        [
          2039,
          0.0162890204535662
        ],
        [
          2040,
          0.0177890032879516
        ],
        [
          2041,
          0.0193657173366638
        ],
        [
          2042,
          0.0210217817461156
        ],
        [
          2043,
          0.0227599626344843
        ],
        [
          2044,
          0.0245831868393934
        ],
        [
          2045,
          0.0264944175797687
        ],
        [
          2046,
          0.0284966728460047
        ],
        [
          2047,
          0.0305931964267929
        ],
        [
          2048,
          0.032787228614641
        ],
        [
          2049,
          0.0350821025366775
        ],
        [
          2050,
          0.0374755643227372
        ],
        [
          2051,
          4.496909888432576e-05
        ]
      ]
    }
  ]
}