{
  "name": "mitigation_cb-315mt~0005",
  "data": [
    {
      "seriesName": "DMD_TRA-P-CAR-BEV",
      "seriesValues": [
        [
          2019,
          3.444
        ],
        [
          2020,
          4.013
        ],
        [
          2021,
          7.899
        ],
        [
          2023,
          34.23136664164619
        ],
        [
          2024,
          61.59134597520101
        ],
        [
          2025,
          110.3957803923126
        ],
        [
          2026,
          103.25423514821553
        ],
        [
          2027,
          99.34465796070758
        ],
        [
          2028,
          142.60368883368582
        ],
        [
          2029,
          163.62450869698682
        ],
        [
          2030,
          199.58700397261845
        ],
        [
          2031,
          254.141893742354
        ],
        [
          2032,
          317.1868084326896
        ],
        [
          2033,
          358.5486524056428
        ],
        [
          2034,
          365.44586377002844
        ],
        [
          2035,
          316.62308950038926
        ],
        [
          2036,
          253.73073985268314
        ],
        [
          2037,
          207.98665114734865
        ],
        [
          2038,
          184.39090083030908
        ],
        [
          2039,
          167.70363640876297
        ],
        [
          2040,
          165.33756926501158
        ],
        [
          2041,
          167.46761286337153
        ],
        [
          2042,
          156.76907328196367
        ],
        [
          2043,
          154.17719493118832
        ],
        [
          2044,
          155.83789207892448
        ],
        [
          2045,
          165.31022768921906
        ],
        [
          2046,
          181.64002035921507
        ],
        [
          2047,
          167.94400484613038
        ],
        [
          2048,
          198.34967509204446
        ],
        [
          2049,
          260.66065739144204
        ],
        [
          2050,
          221.46827130887556
        ],
        [
          2051,
          204.71666518121276
        ]
      ]
    },
    {
      "seriesName": "DMD_TRA-P-CAR-HEV",
      "seriesValues": [
        [
          2019,
          10.193999999999999
        ],
        [
          2020,
          10.986
        ],
        [
          2021,
          18.596
        ],
        [
          2023,
          2.35610725276567e-06
        ],
        [
          2024,
          0.00011204043701381651
        ],
        [
          2025,
          1.1080637637809491e-06
        ],
        [
          2026,
          9.52707337717649e-07
        ],
        [
          2027,
          8.708904110217091e-07
        ],
        [
          2028,
          8.61715510841094e-07
        ],
        [
          2029,
          8.852164595232431e-07
        ],
        [
          2030,
          8.81141842580962e-07
        ],
        [
          2031,
          1.01159744082964e-06
        ],
        [
          2032,
          9.183724736634881e-07
        ],
        [
          2033,
          8.44935335259062e-07
        ],
        [
          2034,
          7.90798957542541e-07
        ],
        [
          2035,
          7.632969452094431e-07
        ],
        [
          2036,
          7.64548727846647e-07
        ],
        [
          2037,
          8.34813905623468e-07
        ],
        [
          2038,
          9.23653602948988e-07
        ],
        [
          2039,
          1.0615801843888659e-06
        ],
        [
          2040,
          1.252559656922745e-06
        ],
        [
          2041,
          1.4396709824196332e-06
        ],
        [
          2042,
          1.713650235880596e-06
        ],
        [
          2043,
          2.152890886810381e-06
        ],
        [
          2044,
          2.9511867815417182e-06
        ],
        [
          2045,
          5.02621282486883e-06
        ],
        [
          2046,
          1.500436370375518e-05
        ],
        [
          2047,
          9.73801373761091e-06
        ],
        [
          2048,
          1.200393380076591e-05
        ],
        [
          2049,
          1.882282059711029e-05
        ],
        [
          2050,
          1.958475858949714e-05
        ],
        [
          2051,
          4.7962376389682604e-05
        ]
      ]
    },
    {
      "seriesName": "DMD_TRA-P-CAR-PHEV",
      "seriesValues": [
        [
          2019,
          1.3459999999999999
        ],
        [
          2020,
          2.492
        ],
        [
          2021,
          7.516
        ],
        [
          2022,
          7.32608943956517e-07
        ],
        [
          2023,
          29.533373539787835
        ],
        [
          2024,
          53.18599242620799
        ],
        [
          2025,
          3.150034008986471e-05
        ],
        [
          2026,
          2.255706096372637e-05
        ],
        [
          2027,
          2.061240336615694e-05
        ],
        [
          2028,
          2.058570112821777e-05
        ],
        [
          2029,
          2.41730583451156e-05
        ],
        [
          2030,
          6.969670410641176e-05
        ],
        [
          2031,
          0.0004929051906316766
        ],
        [
          2032,
          9.562819328638936e-06
        ],
        [
          2033,
          5.756190161257154e-06
        ],
        [
          2034,
          4.408740047373465e-06
        ],
        [
          2035,
          4.266776907584387e-06
        ],
        [
          2036,
          4.596417428224743e-06
        ],
        [
          2037,
          5.9633464820414055e-06
        ],
        [
          2038,
          6.859597484704939e-06
        ],
        [
          2039,
          9.241774185730084e-06
        ],
        [
          2040,
          1.2735428037890833e-05
        ],
        [
          2041,
          1.541717272140059e-05
        ],
        [
          2042,
          1.8906490736012256e-05
        ],
        [
          2043,
          2.4175485160664303e-05
        ],
        [
          2044,
          4.0487043171987e-05
        ],
        [
          2045,
          8.153441121425007e-05
        ],
        [
          2046,
          0.0004175585516245782
        ],
        [
          2047,
          0.00010428134238271835
        ],
        [
          2048,
          0.0010529221890002753
        ],
        [
          2049,
          0.002571374517775944
        ],
        [
          2050,
          0.0005076270770647219
        ],
        [
          2051,
          0.0008827727244713948
        ]
      ]
    },
    {
      "seriesName": "DMD_TRA-P-CAR-ICE",
      "seriesValues": [
        [
          2021,
          66.964
        ],
        [
          2022,
          6.20490963346999e-08
        ],
        [
          2023,
          9.430449377950796e-06
        ],
        [
          2024,
          322.33183847127276
        ],
        [
          2025,
          3.186223528708057e-06
        ],
        [
          2026,
          3.433347536233784e-06
        ],
        [
          2027,
          6.11686892988377e-06
        ],
        [
          2028,
          11.878870043927842
        ],
        [
          2029,
          3.985643372312306e-06
        ],
        [
          2030,
          5.622519888552502e-06
        ],
        [
          2031,
          8.464729107554189e-06
        ],
        [
          2032,
          6.274728291042491e-06
        ],
        [
          2033,
          6.443726299092169e-06
        ],
        [
          2034,
          3.9063756970650215e-06
        ],
        [
          2035,
          3.3978415315428447e-06
        ],
        [
          2036,
          4.485798620588248e-06
        ],
        [
          2037,
          4.355124243339584e-06
        ],
        [
          2038,
          5.292022131574527e-06
        ],
        [
          2039,
          6.074398074816879e-06
        ],
        [
          2040,
          9.328585140134318e-06
        ],
        [
          2041,
          1.535797108329e-05
        ],
        [
          2042,
          7.738877534694095
        ],
        [
          2043,
          7.90242888618805
        ],
        [
          2044,
          3.318999235890997e-05
        ],
        [
          2045,
          2.2137214318804987e-05
        ],
        [
          2046,
          1.7244204121737603
        ],
        [
          2047,
          3.147145925770884e-05
        ],
        [
          2048,
          1.5982271323607496e-05
        ],
        [
          2049,
          2.250869975945086e-05
        ],
        [
          2050,
          3.3592885884478e-05
        ],
        [
          2051,
          9.149879773136454e-05
        ]
      ]
    },
    {
      "seriesName": "DMD_TRA-P-CAR-FCV",
      "seriesValues": [
        [
          2030,
          1.51199765414276e-06
        ],
        [
          2031,
          1.74632221870688e-06
        ],
        [
          2032,
          1.13555198342734e-06
        ],
        [
          2033,
          8.89664108665623e-07
        ],
        [
          2034,
          7.15164548019764e-07
        ],
        [
          2035,
          7.65084185362553e-07
        ],
        [
          2036,
          7.37038019288824e-07
        ],
        [
          2037,
          8.56262440394163e-07
        ],
        [
          2038,
          8.99178254964894e-07
        ],
        [
          2039,
          1.05023031663005e-06
        ],
        [
          2040,
          1.22466265502356e-06
        ],
        [
          2041,
          1.42567791149639e-06
        ],
        [
          2042,
          1.71423798884972e-06
        ],
        [
          2043,
          2.18516764939452e-06
        ],
        [
          2044,
          2.52767438258434e-06
        ],
        [
          2045,
          3.22094308181927e-06
        ],
        [
          2046,
          3.29219581105561e-06
        ],
        [
          2047,
          4.49516833483064e-06
        ],
        [
          2048,
          7.53004154475892e-06
        ],
        [
          2049,
          9.19589785291934e-06
        ],
        [
          2050,
          1.30872468249163e-05
        ],
        [
          2051,
          1.74255413232653e-05
        ]
      ]
    }
  ]
}